LICENSE
stellar_model/__init__.py
stellar_model/model/__init__.py
stellar_model/model/horizon/__init__.py
stellar_model/model/horizon/account.py
stellar_model/model/horizon/account_data.py
stellar_model/model/horizon/asset.py
stellar_model/model/horizon/asset_stat.py
stellar_model/model/horizon/async_transaction.py
stellar_model/model/horizon/claimable_balance.py
stellar_model/model/horizon/effects.py
stellar_model/model/horizon/fee_stats.py
stellar_model/model/horizon/ledger.py
stellar_model/model/horizon/link.py
stellar_model/model/horizon/liquidity_pool.py
stellar_model/model/horizon/liquidity_pool_asset_amount.py
stellar_model/model/horizon/offer.py
stellar_model/model/horizon/operations.py
stellar_model/model/horizon/order_book_summary.py
stellar_model/model/horizon/path.py
stellar_model/model/horizon/price.py
stellar_model/model/horizon/root.py
stellar_model/model/horizon/trade.py
stellar_model/model/horizon/trade_aggregation.py
stellar_model/model/horizon/transaction.py
stellar_model/py.typed
stellar_model/response/__init__.py
stellar_model/response/account_data_response.py
stellar_model/response/account_response.py
stellar_model/response/accounts_response.py
stellar_model/response/assets_response.py
stellar_model/response/async_transaction_response.py
stellar_model/response/claimable_balance_response.py
stellar_model/response/claimable_balances_response.py
stellar_model/response/effect_response.py
stellar_model/response/effects_response.py
stellar_model/response/error_response.py
stellar_model/response/fee_stats_response.py
stellar_model/response/ledger_response.py
stellar_model/response/ledgers_response.py
stellar_model/response/liquidity_pool_response.py
stellar_model/response/liquidity_pools_response.py
stellar_model/response/offer_response.py
stellar_model/response/offers_response.py
stellar_model/response/operation_response.py
stellar_model/response/operations_response.py
stellar_model/response/order_book_response.py
stellar_model-0.7.0.dist-info/LICENSE
stellar_model-0.7.0.dist-info/METADATA
stellar_model-0.7.0.dist-info/WHEEL
stellar_model-0.7.0.dist-info/RECORD
