Metadata-Version: 2.1
Name: stellar-model
Version: 0.7.0
Summary: Parse the raw Stellar data into Python models.
Home-page: https://github.com/StellarCN/stellar-model
License: Apache-2.0
Keywords: stellar,stellar-model,pydantic
Author: overcat
Author-email: 4catcode@gmail.com
Requires-Python: >=3.8
Classifier: Development Status :: 4 - Beta
Classifier: Intended Audience :: Developers
Classifier: License :: OSI Approved :: Apache Software License
Classifier: Natural Language :: English
Classifier: Operating System :: OS Independent
Classifier: Programming Language :: Python
Classifier: Programming Language :: Python :: 3
Classifier: Programming Language :: Python :: 3.8
Classifier: Programming Language :: Python :: 3.9
Classifier: Programming Language :: Python :: 3.10
Classifier: Programming Language :: Python :: 3.11
Classifier: Programming Language :: Python :: 3.12
Classifier: Programming Language :: Python :: 3.13
Classifier: Programming Language :: Python :: 3 :: Only
Classifier: Programming Language :: Python :: 3.6
Classifier: Programming Language :: Python :: 3.7
Classifier: Programming Language :: Python :: Implementation :: CPython
Classifier: Programming Language :: Python :: Implementation :: PyPy
Classifier: Topic :: Software Development :: Libraries :: Python Modules
Classifier: Typing :: Typed
Requires-Dist: pydantic (>=2.9.2,<3.0.0)
Project-URL: Bug Tracker, https://github.com/StellarCN/stellar-mode/issues
Project-URL: Documentation, https://stellar-model.readthedocs.io
Project-URL: Repository, https://github.com/StellarCN/stellar-model
